system_monitor/__init__.py
system_monitor/admin.py
system_monitor/api/__init__.py
system_monitor/api/paginations/__init__.py
system_monitor/api/paginations/limit_offset_pagination.py
system_monitor/api/serializers/__init__.py
system_monitor/api/serializers/resource_usage.py
system_monitor/api/throttlings/__init__.py
system_monitor/api/throttlings/role_base_throttle.py
system_monitor/api/views/__init__.py
system_monitor/api/views/resource_usage.py
system_monitor/apps.py
system_monitor/calculator.py
system_monitor/constants/__init__.py
system_monitor/constants/default_settings.py
system_monitor/constants/types.py
system_monitor/management/__init__.py
system_monitor/management/commands/__init__.py
system_monitor/management/commands/collect_metrics.py
system_monitor/migrations/0001_initial.py
system_monitor/migrations/__init__.py
system_monitor/mixins/__init__.py
system_monitor/mixins/api/__init__.py
system_monitor/mixins/api/config_api_attrs.py
system_monitor/mixins/api/control_api_methods.py
system_monitor/models.py
system_monitor/settings/__init__.py
system_monitor/settings/checks.py
system_monitor/settings/conf.py
system_monitor/templates/dashboard.html
system_monitor/tests/__init__.py
system_monitor/tests/admin/__init__.py
system_monitor/tests/admin/test_resource_usage.py
system_monitor/tests/api/__init__.py
system_monitor/tests/api/paginations/__init__.py
system_monitor/tests/api/paginations/test_limit_offset_pagination.py
system_monitor/tests/api/throttlings/__init__.py
system_monitor/tests/api/throttlings/test_role_base_throttle.py
system_monitor/tests/api/views/__init__.py
system_monitor/tests/api/views/test_resource_usage.py
system_monitor/tests/calculator/__init__.py
system_monitor/tests/calculator/test_calculator.py
system_monitor/tests/commands/__init__.py
system_monitor/tests/commands/test_collect_metrics.py
system_monitor/tests/conftest.py
system_monitor/tests/constants.py
system_monitor/tests/fixtures/__init__.py
system_monitor/tests/fixtures/admin.py
dj_system_monitor-1.0.1.dist-info/AUTHORS.md
dj_system_monitor-1.0.1.dist-info/LICENSE
dj_system_monitor-1.0.1.dist-info/METADATA
dj_system_monitor-1.0.1.dist-info/WHEEL
dj_system_monitor-1.0.1.dist-info/RECORD
